Metadata-Version: 2.1
Name: flask-appbuilder
Version: 5.0.2
Summary: Simple and rapid application development framework, built on top of Flask. includes detailed security, auto CRUD generation for your models, google charts and much more.
Home-page: https://github.com/dpgaspar/flask-appbuilder/
Author: Daniel Vaz Gaspar
Author-email: danielvazgaspar@gmail.com
License: BSD
Platform: any
Classifier: Development Status :: 5 - Production/Stable
Classifier: Environment :: Web Environment
Classifier: Intended Audience :: Developers
Classifier: License :: OSI Approved :: BSD License
Classifier: Operating System :: OS Independent
Classifier: Programming Language :: Python :: 3.8
Classifier: Programming Language :: Python :: 3.9
Classifier: Programming Language :: Python :: 3.10
Classifier: Programming Language :: Python :: 3.11
Classifier: Programming Language :: Python :: 3.12
Classifier: Topic :: Software Development :: Libraries :: Python Modules
Requires-Python: ~=3.7
License-File: LICENSE
Requires-Dist: apispec[yaml] <7,>=6.0.0
Requires-Dist: colorama <1,>=0.3.9
Requires-Dist: click <9,>=8
Requires-Dist: email-validator >=1.0.5
Requires-Dist: Flask <4,>=2
Requires-Dist: Flask-Babel <5,>=3
Requires-Dist: Flask-Limiter <4,>3
Requires-Dist: Flask-Login <0.7,>=0.3
Requires-Dist: Flask-SQLAlchemy <4,>=2.4.0
Requires-Dist: Flask-WTF <2,>=0.14.2
Requires-Dist: Flask-JWT-Extended <5.0.0,>=4.0.0
Requires-Dist: jsonschema <5,>=3
Requires-Dist: marshmallow <5,>=3.18.0
Requires-Dist: marshmallow-sqlalchemy <3.0.0,>=0.22.0
Requires-Dist: python-dateutil <3,>=2.3
Requires-Dist: prison <1.0.0,>=0.2.1
Requires-Dist: PyJWT <3.0.0,>=2.0.0
Requires-Dist: SQLAlchemy <3,>=1.4.0
Requires-Dist: sqlalchemy-utils <1,>=0.32.21
Requires-Dist: WTForms <4
Requires-Dist: werkzeug <4
Provides-Extra: jmespath
Requires-Dist: jmespath >=0.9.5 ; extra == 'jmespath'
Provides-Extra: oauth
Requires-Dist: Authlib <2.0.0,>=0.14 ; extra == 'oauth'
Provides-Extra: talisman
Requires-Dist: flask-talisman <2.0,>=1.0.0 ; extra == 'talisman'
